trepan/__init__.py
trepan/__main__.py
trepan/api.py
trepan/bwcli.py
trepan/client.py
trepan/clifns.py
trepan/debugger.py
trepan/exception.py
trepan/interface.py
trepan/misc.py
trepan/options.py
trepan/post_mortem.py
trepan/version.py
trepan/vprocessor.py
trepan/bwprocessor/__init__.py
trepan/bwprocessor/location.py
trepan/bwprocessor/main.py
trepan/bwprocessor/msg.py
trepan/inout/__init__.py
trepan/inout/base.py
trepan/inout/fifoclient.py
trepan/inout/fifoserver.py
trepan/inout/input.py
trepan/inout/output.py
trepan/inout/scriptin.py
trepan/inout/stringarray.py
trepan/inout/tcpclient.py
trepan/inout/tcpfns.py
trepan/inout/tcpserver.py
trepan/interfaces/__init__.py
trepan/interfaces/bullwinkle.py
trepan/interfaces/client.py
trepan/interfaces/comcodes.py
trepan/interfaces/script.py
trepan/interfaces/server.py
trepan/interfaces/user.py
trepan/lib/__init__.py
trepan/lib/breakpoint.py
trepan/lib/bytecode.py
trepan/lib/complete.py
trepan/lib/core.py
trepan/lib/default.py
trepan/lib/deparse.py
trepan/lib/disassemble.py
trepan/lib/display.py
trepan/lib/eval.py
trepan/lib/file.py
trepan/lib/format.py
trepan/lib/pp.py
trepan/lib/printing.py
trepan/lib/sighandler.py
trepan/lib/stack.py
trepan/lib/thred.py
trepan/processor/__init__.py
trepan/processor/cmd_addrlist.py
trepan/processor/cmdbreak.py
trepan/processor/cmdfns.py
trepan/processor/cmdlist.py
trepan/processor/cmdproc.py
trepan/processor/complete.py
trepan/processor/frame.py
trepan/processor/location.py
trepan/processor/subcmd.py
trepan/processor/trace.py
trepan/processor/command/__init__.py
trepan/processor/command/alias.py
trepan/processor/command/backtrace.py
trepan/processor/command/base_cmd.py
trepan/processor/command/base_subcmd.py
trepan/processor/command/base_submgr.py
trepan/processor/command/bpy.py
trepan/processor/command/break.py
trepan/processor/command/cd.py
trepan/processor/command/clear.py
trepan/processor/command/condition.py
trepan/processor/command/continue.py
trepan/processor/command/debug.py
trepan2-1.2.9.dist-info/COPYING
trepan2-1.2.9.dist-info/METADATA
trepan2-1.2.9.dist-info/WHEEL
trepan2-1.2.9.dist-info/entry_points.txt
trepan2-1.2.9.dist-info/top_level.txt
trepan2-1.2.9.dist-info/RECORD
