Metadata-Version: 2.1
Name: trepan2
Version: 1.2.9
Summary: GDB-like Python Debugger in the Trepan family
Home-page: http://github.com/rocky/python2-trepan/
Author: Rocky Bernstein
Author-email: rocky@gnu.org
License: GPL3
Platform: UNKNOWN
Classifier: Development Status :: 5 - Production/Stable
Classifier: Environment :: Console
Classifier: Intended Audience :: Developers
Classifier: License :: OSI Approved :: GNU General Public License v3 (GPLv3)
Classifier: Operating System :: OS Independent
Classifier: Programming Language :: Python
Classifier: Topic :: Software Development :: Debuggers
Classifier: Topic :: Software Development :: Libraries :: Python Modules
Classifier: Programming Language :: Python :: 2.4
Classifier: Programming Language :: Python :: 2.5
Classifier: Programming Language :: Python :: 2.6
Classifier: Programming Language :: Python :: 2.7
Classifier: Programming Language :: Python :: Implementation :: PyPy
Requires-Dist: columnize (>=0.3.10)
Requires-Dist: nose (<=1.3.7,>=1.0.0)
Requires-Dist: pyficache (>=2.3.0)
Requires-Dist: pygments (<=2.2.5,>=2.2.0)
Requires-Dist: spark-parser (<1.9.0,>=1.8.9)
Requires-Dist: uncompyle6 (>=3.9.2)
Requires-Dist: term-background (>=1.0.1)
Requires-Dist: tracer (>=0.3.2)
Requires-Dist: unittest2
Requires-Dist: xdis (<6.2.0,>=6.1.1)
